README.rst
setup.cfg
setup.py
pymetis_mesh/__init__.pxd
pymetis_mesh/__init__.py
pymetis_mesh/_parwrapper.c
pymetis_mesh/_parwrapper.pyx
pymetis_mesh/_version.py
pymetis_mesh/_wrapper.c
pymetis_mesh/_wrapper.pxd
pymetis_mesh/_wrapper.pyx
pymetis_mesh/errors.py
pymetis_mesh/mpi-compat.h
pymetis_mesh/parmetis.pxd
pymetis_mesh/parmetis.py
pymetis_mesh.egg-info/PKG-INFO
pymetis_mesh.egg-info/SOURCES.txt
pymetis_mesh.egg-info/dependency_links.txt
pymetis_mesh.egg-info/requires.txt
pymetis_mesh.egg-info/top_level.txt
pymetis_mesh/src/include/CMakeLists.txt
pymetis_mesh/src/include/parmetis.h
pymetis_mesh/src/libparmetis/CMakeLists.txt
pymetis_mesh/src/libparmetis/akwayfm.c
pymetis_mesh/src/libparmetis/ametis.c
pymetis_mesh/src/libparmetis/balancemylink.c
pymetis_mesh/src/libparmetis/comm.c
pymetis_mesh/src/libparmetis/csrmatch.c
pymetis_mesh/src/libparmetis/ctrl.c
pymetis_mesh/src/libparmetis/debug.c
pymetis_mesh/src/libparmetis/defs.h
pymetis_mesh/src/libparmetis/diffutil.c
pymetis_mesh/src/libparmetis/frename.c
pymetis_mesh/src/libparmetis/gkmetis.c
pymetis_mesh/src/libparmetis/gkmpi.c
pymetis_mesh/src/libparmetis/graph.c
pymetis_mesh/src/libparmetis/initbalance.c
pymetis_mesh/src/libparmetis/initmsection.c
pymetis_mesh/src/libparmetis/initpart.c
pymetis_mesh/src/libparmetis/kmetis.c
pymetis_mesh/src/libparmetis/kwayrefine.c
pymetis_mesh/src/libparmetis/macros.h
pymetis_mesh/src/libparmetis/match.c
pymetis_mesh/src/libparmetis/mdiffusion.c
pymetis_mesh/src/libparmetis/mesh.c
pymetis_mesh/src/libparmetis/mmetis.c
pymetis_mesh/src/libparmetis/move.c
pymetis_mesh/src/libparmetis/msetup.c
pymetis_mesh/src/libparmetis/node_refine.c
pymetis_mesh/src/libparmetis/ometis.c
pymetis_mesh/src/libparmetis/parmetislib.h
pymetis_mesh/src/libparmetis/proto.h
pymetis_mesh/src/libparmetis/pspases.c
pymetis_mesh/src/libparmetis/redomylink.c
pymetis_mesh/src/libparmetis/remap.c
pymetis_mesh/src/libparmetis/rename.h
pymetis_mesh/src/libparmetis/renumber.c
pymetis_mesh/src/libparmetis/rmetis.c
pymetis_mesh/src/libparmetis/selectq.c
pymetis_mesh/src/libparmetis/serial.c
pymetis_mesh/src/libparmetis/stat.c
pymetis_mesh/src/libparmetis/struct.h
