Metadata-Version: 1.1
Name: pymetis-mesh
Version: 1.0.0
Summary: Partitioning Finite Element Meshes with METIS in Python
Home-page: https://github.com/chiao45/pymetis_mesh
Author: Qiao Chen
Author-email: benechiao@gmail.com
License: MIT
Keywords: Math
Platform: UNKNOWN
Classifier: Programming Language :: Python
Classifier: Programming Language :: Python :: 2.7
Classifier: Programming Language :: Python :: 3.4
Classifier: Programming Language :: Python :: 3.5
Classifier: Programming Language :: Python :: 3.6
Classifier: License :: OSI Approved :: MIT License
Classifier: Topic :: Scientific/Engineering
Classifier: Topic :: Software Development
Classifier: Operating System :: POSIX :: Linux
Classifier: Intended Audience :: Science/Research
